coptpy-stubs/__init__.pyi
coptpy-stubs/coptpy.pyi
coptpy_stubs-1.1.5.dist-info/METADATA
coptpy_stubs-1.1.5.dist-info/WHEEL
coptpy_stubs-1.1.5.dist-info/top_level.txt
coptpy_stubs-1.1.5.dist-info/RECORD
